conda_mirror/__init__.py
conda_mirror/_version.py
conda_mirror/conda_mirror.py
conda_mirror/diff_tar.py
conda_mirror/versionspec.py
conda_mirror-0.10.0.dist-info/AUTHORS.md
conda_mirror-0.10.0.dist-info/LICENSE
conda_mirror-0.10.0.dist-info/METADATA
conda_mirror-0.10.0.dist-info/WHEEL
conda_mirror-0.10.0.dist-info/entry_points.txt
conda_mirror-0.10.0.dist-info/top_level.txt
conda_mirror-0.10.0.dist-info/RECORD
