Metadata-Version: 2.1
Name: conda-mirror
Version: 0.10.0
Summary: Mirror an upstream conda channel to a local directory
Home-page: https://github.com/regro/conda-mirror
Author: Eric Dill
Author-email: eric.dill@maxpoint.com
License: BSD 3-Clause
Platform: Linux
Platform: Mac OSX
Platform: Windows
Requires-Dist: requests
Requires-Dist: pyyaml
Requires-Dist: tqdm
